whodap/__init__.py
whodap/client.py
whodap/codes.py
whodap/errors.py
whodap/response.py
whodap/utils.py
whodap-0.1.13.dist-info/licenses/LICENSE.txt
whodap-0.1.13.dist-info/METADATA
whodap-0.1.13.dist-info/WHEEL
whodap-0.1.13.dist-info/top_level.txt
whodap-0.1.13.dist-info/RECORD
