Metadata-Version: 2.4
Name: whodap
Version: 0.1.13
Summary: Simple RDAP Utility for Python
Home-page: https://github.com/pogzyb/whodap
Author: Joseph Obarzanek
Author-email: pogzyb@umich.edu
Project-URL: Bug Tracker, https://github.com/pogzyb/whodap/issues
Keywords: security,whois,rdap,research
Classifier: Development Status :: 3 - Alpha
Classifier: Intended Audience :: Developers
Classifier: Topic :: Software Development
Classifier: Topic :: Security
Classifier: License :: OSI Approved :: MIT License
Classifier: Programming Language :: Python :: 3
Classifier: Programming Language :: Python :: 3.6
Classifier: Programming Language :: Python :: 3.7
Classifier: Programming Language :: Python :: 3.8
Classifier: Programming Language :: Python :: 3.9
Classifier: Programming Language :: Python :: 3.10
Classifier: Programming Language :: Python :: 3.11
Classifier: Programming Language :: Python :: 3 :: Only
Requires-Python: >=3.6, <4
License-File: LICENSE.txt
Requires-Dist: httpx>=0.20.0
Requires-Dist: async_generator>=1.10; python_version < "3.7.0"
Dynamic: author
Dynamic: author-email
Dynamic: classifier
Dynamic: description
Dynamic: description-content-type
Dynamic: home-page
Dynamic: keywords
Dynamic: license-file
Dynamic: requires-dist
Dynamic: requires-python
Dynamic: summary
